vault_cli/__init__.py
vault_cli/__main__.py
vault_cli/cli.py
vault_cli/client.py
vault_cli/environment.py
vault_cli/exceptions.py
vault_cli/metadata.py
vault_cli/sessions.py
vault_cli/settings.py
vault_cli/ssh.py
vault_cli/testing.py
vault_cli/types.py
vault_cli/utils.py
vault_cli-3.1.0.dist-info/LICENSE
vault_cli-3.1.0.dist-info/METADATA
vault_cli-3.1.0.dist-info/WHEEL
vault_cli-3.1.0.dist-info/entry_points.txt
vault_cli-3.1.0.dist-info/top_level.txt
vault_cli-3.1.0.dist-info/zip-safe
vault_cli-3.1.0.dist-info/RECORD
