Metadata-Version: 2.1
Name: vault-cli
Version: 3.1.0
Summary: CLI tool for hashicorp vault
Home-page: https://github.com/peopledoc/vault-cli
Author: PeopleDoc
Author-email: joachim.jablon@people-doc.com
License: Apache Software License
Keywords: hashicorp vault cli
Platform: UNKNOWN
Classifier: Development Status :: 4 - Beta
Classifier: Intended Audience :: Developers
Classifier: License :: OSI Approved :: Apache Software License
Classifier: Programming Language :: Python :: 3
Classifier: Programming Language :: Python :: 3.6
Classifier: Programming Language :: Python :: 3.7
License-File: LICENSE
Requires-Dist: requests
Requires-Dist: Click (>=7.0)
Requires-Dist: pyyaml (>=5.3.1)
Requires-Dist: jinja2
Requires-Dist: hvac (<0.10.12)
Provides-Extra: dev
Requires-Dist: tox ; extra == 'dev'
Requires-Dist: twine ; extra == 'dev'
Requires-Dist: black ; extra == 'dev'
Requires-Dist: isort ; extra == 'dev'
Requires-Dist: build ; extra == 'dev'
Provides-Extra: docs
Requires-Dist: doc8 ; extra == 'docs'
Requires-Dist: sphinx ; extra == 'docs'
Requires-Dist: sphinx-autodoc-typehints ; extra == 'docs'
Requires-Dist: sphinxcontrib-programoutput ; extra == 'docs'
Provides-Extra: docs_spelling
Requires-Dist: sphinxcontrib-spelling ; extra == 'docs_spelling'
Provides-Extra: lint
Requires-Dist: mypy ; extra == 'lint'
Requires-Dist: flake8 ; extra == 'lint'
Requires-Dist: black ; extra == 'lint'
Requires-Dist: isort ; extra == 'lint'
Requires-Dist: types-PyYAML ; extra == 'lint'
Requires-Dist: types-requests ; extra == 'lint'
Requires-Dist: types-setuptools ; extra == 'lint'
Requires-Dist: types-toml ; extra == 'lint'
Provides-Extra: test
Requires-Dist: pytest ; extra == 'test'
Requires-Dist: pytest-mock ; extra == 'test'
Requires-Dist: requests-mock ; extra == 'test'
Requires-Dist: pytest-cov ; extra == 'test'
Requires-Dist: pytest-click ; extra == 'test'
Provides-Extra: testing
Requires-Dist: pytest ; extra == 'testing'
